Workbook
Name aporte: App!$D$16:$D$16
Name patrimonio_acumulado: App!$D$19:$D$19
Name qtd_anos: App!$D$17:$D$17
Name rendimento_carteira: App!$E$12:$E$12
Name sugestao_investimento: App!$E$13:$E$13
Name taxa_mensal: App!$D$18:$D$18

Sheet App
B10: Configurações
B11: Salário | E11: 5000
B12: Rendimento Carteira | E12: 0.01
B13: Sugestão de Investimento (30%) | E13: =E11*30% -> 1500
B15: INVESTIMENTO MENSAL
B16: Quanto investir por mês? | D16: 500
B17: Por quantos anos? | D17: 5
B18: Taxa de Rendimento Mensal | D18: 0.01079
B19: Patrimônio Acumulado | D19: {=FV(taxa_mensal,qtd_anos*12,aporte*-1)} -> 41888.457
B20: Dividendos Mensais | D20: {=patrimonio_acumulado*rendimento_carteira} -> 418.88457
B22: CENÁRIOS | D22: Dividendo
A23: 2 | B23: Quanto em 2 anos? | C23: {=FV(taxa_mensal,$A23*12,aporte*-1)} -> 13613.814 | D23: {=$C23*rendimento_carteira} -> 136.13814
A24: 5 | B24: Quanto em 5 anos? | C24: {=FV(taxa_mensal,$A24*12,aporte*-1)} -> 41888.457 | D24: {=$C24*rendimento_carteira} -> 418.88457
A25: 10 | B25: Quanto em 10 anos? | C25: {=FV(taxa_mensal,$A25*12,aporte*-1)} -> 121642.11 | D25: {=$C25*rendimento_carteira} -> 1216.4211
A26: 20 | B26: Quanto em 20 anos? | C26: {=FV(taxa_mensal,$A26*12,aporte*-1)} -> 562599.2 | D26: {=$C26*rendimento_carteira} -> 5625.992
A27: 30 | B27: Quanto em 30 anos? | C27: {=FV(taxa_mensal,$A27*12,aporte*-1)} -> 2161084.8 | D27: {=$C27*rendimento_carteira} -> 21610.848
B30: Perfil | D30: Agressivo
B31: Valor a ser investido por mês | D31: {=aporte} -> 500
B33: TIPO DE FII | D33: Percentual Sugerido | E33: Valores
B34: PAPEL | D34: =VLOOKUP($D$30&"-"&B34,Perfis!A3:D20,4,0) -> 0.5 | E34: =D34*$D$31 -> 250
B35: TIJOLO | D35: =VLOOKUP($D$30&"-"&B35,Perfis!A4:D21,4,0) -> 0.1 | E35: =D35*$D$31 -> 50
B36: HÍBRIDOS | D36: =VLOOKUP($D$30&"-"&B36,Perfis!A5:D22,4,0) -> 0.05 | E36: =D36*$D$31 -> 25
B37: FOFs | D37: =VLOOKUP($D$30&"-"&B37,Perfis!A6:D23,4,0) -> 0.05 | E37: =D37*$D$31 -> 25
B38: DESENVOLVIMENTO | D38: =VLOOKUP($D$30&"-"&B38,Perfis!A7:D24,4,0) -> 0.2 | E38: =D38*$D$31 -> 100
B39: HOTELARIAS | D39: =VLOOKUP($D$30&"-"&B39,Perfis!A8:D25,4,0) -> 0.1 | E39: =D39*$D$31 -> 50
B40: TOTAL | E40: =SUM(E34:E39) -> 500

Sheet Perfis
A2: CHAVE | B2: PERFIL | C2: TIPO | D2: %
A3: =B3&"-"&C3 -> Conservador-PAPEL | B3: Conservador | C3: PAPEL | D3: 0.3
A4: =B4&"-"&C4 -> Conservador-TIJOLO | B4: Conservador | C4: TIJOLO | D4: 0.5
A5: =B5&"-"&C5 -> Conservador-HÍBRIDOS | B5: Conservador | C5: HÍBRIDOS | D5: 0.1
A6: =B6&"-"&C6 -> Conservador-FOFs | B6: Conservador | C6: FOFs | D6: 0.1
A7: =B7&"-"&C7 -> Conservador-DESENVOLVIMENTO | B7: Conservador | C7: DESENVOLVIMENTO | D7: 0
A8: =B8&"-"&C8 -> Conservador-HOTELARIAS | B8: Conservador | C8: HOTELARIAS | D8: 0
A9: =B9&"-"&C9 -> Moderado-PAPEL | B9: Moderado | C9: PAPEL | D9: 0.32
A10: =B10&"-"&C10 -> Moderado-TIJOLO | B10: Moderado | C10: TIJOLO | D10: 0.4
A11: =B11&"-"&C11 -> Moderado-HÍBRIDOS | B11: Moderado | C11: HÍBRIDOS | D11: 0.08
A12: =B12&"-"&C12 -> Moderado-FOFs | B12: Moderado | C12: FOFs | D12: 0.1
A13: =B13&"-"&C13 -> Moderado-DESENVOLVIMENTO | B13: Moderado | C13: DESENVOLVIMENTO | D13: 0.1
A14: =B14&"-"&C14 -> Moderado-HOTELARIAS | B14: Moderado | C14: HOTELARIAS | D14: 0
... A20: =B20&"-"&C20 -> Agressivo-HOTELARIAS | B20: Agressivo | C20: HOTELARIAS | D20: 0.1
